domreducer/__init__.py
domreducer/reducer.py
domreducer/schemes.py
domreducer/test_run.py
domreducer-0.0.4.dist-info/METADATA
domreducer-0.0.4.dist-info/WHEEL
domreducer-0.0.4.dist-info/top_level.txt
domreducer-0.0.4.dist-info/RECORD
